bresourcemanager/__init__.py
bresourcemanager-0.0.2.dist-info/METADATA
bresourcemanager-0.0.2.dist-info/WHEEL
bresourcemanager-0.0.2.dist-info/licenses/LICENSE
bresourcemanager-0.0.2.dist-info/RECORD
