Metadata-Version: 2.3
Name: bresourcemanager
Version: 0.0.2
Summary: bresourcemanager
Project-URL: Source, https://github.com/b-scheduler/bresourcemanager
Author-email: wh1isper <jizhongsheng957@gmail.com>
License: BSD 3-Clause License
License-File: LICENSE
Keywords: bresourcemanager
Classifier: Programming Language :: Python :: 3
Classifier: Programming Language :: Python :: 3.10
Classifier: Programming Language :: Python :: 3.11
Classifier: Programming Language :: Python :: 3.12
Requires-Python: >=3.10
Provides-Extra: docs
Requires-Dist: autodoc-pydantic; extra == 'docs'
Requires-Dist: pydata-sphinx-theme; extra == 'docs'
Requires-Dist: sphinx; extra == 'docs'
Requires-Dist: sphinx-click; extra == 'docs'
Provides-Extra: test
Requires-Dist: docker; extra == 'test'
Requires-Dist: pytest; extra == 'test'
Requires-Dist: pytest-asyncio; extra == 'test'
Requires-Dist: pytest-cov; extra == 'test'
